{
  "$schema": "https://ui.shadcn.com/schema/registry-item.json",
  "name": "theme-hud-cyan",
  "type": "registry:theme",
  "title": "HUD Theme — Cyan Accent",
  "description": "Cyan accent override for the HUD theme. Install after theme-hud; warnings and destructive tones stay warm.",
  "cssVars": {
    "dark": {
      "primary": "#33D1FF",
      "primary-bright": "#7AE0FF",
      "ring": "#33D1FF",
      "chart-1": "#33D1FF",
      "sidebar-primary": "#33D1FF",
      "sidebar-ring": "#33D1FF"
    }
  }
}
